PyKagi/__init__.py
PyKagi/api.py
PyKagi/config/__init__.py
PyKagi/config/info.py
PyKagi-0.0.4.dist-info/LICENSE
PyKagi-0.0.4.dist-info/METADATA
PyKagi-0.0.4.dist-info/WHEEL
PyKagi-0.0.4.dist-info/top_level.txt
PyKagi-0.0.4.dist-info/RECORD
