Metadata-Version: 2.1
Name: PyKagi
Version: 0.0.4
Summary: Kagi API Python Wrapper
Home-page: https://github.com/WooilJeong/PyKagi
Author: 정우일(Wooil Jeong)
Author-email: wooil@kakao.com
License: MIT
Platform: UNKNOWN
Classifier: Programming Language :: Python :: 3
Classifier: License :: OSI Approved :: Apache Software License
Classifier: Operating System :: OS Independent
License-File: LICENSE
Requires-Dist: certifi (==2022.12.7)
Requires-Dist: charset-normalizer (==3.1.0)
Requires-Dist: idna (==3.4)
Requires-Dist: requests (==2.28.2)
Requires-Dist: urllib3 (==1.26.15)
